{
    "nl": "/home/edabk/Desktop/Tu67/MARCO_ultra/Branch_Metrics/runs/Branch_Metrics_run/06-yosys-synthesis/Branch_Metrics.nl.v",
    "pnl": null,
    "pnl-sdf-friendly": null,
    "pnl-npc": null,
    "def": null,
    "lef": null,
    "openroad-lef": null,
    "odb": null,
    "sdc": null,
    "sdf": null,
    "spef": null,
    "lib": null,
    "spice": null,
    "mag": null,
    "gds": null,
    "mag_gds": null,
    "klayout_gds": null,
    "json_h": "/home/edabk/Desktop/Tu67/MARCO_ultra/Branch_Metrics/runs/Branch_Metrics_run/05-yosys-jsonheader/Branch_Metrics.h.json",
    "vh": null,
    "metrics": {
        "design__lint_error__count": 0,
        "design__lint_timing_construct__count": 0,
        "design__lint_warning__count": 32,
        "design__inferred_latch__count": 0,
        "design__instance__count": 16,
        "design__instance__area": 113.8592,
        "design__instance_unmapped__count": 0,
        "synthesis__check_error__count": 0
    }
}